Metadata-Version: 2.1
Name: AegosInfo
Version: 0.1
Summary: Giting info account in instagram .
Author: AegosInfo
Author-email: syakkml@gmail.com
Classifier: Programming Language :: Python :: 3
Classifier: Operating System :: OS Independent
Classifier: License :: OSI Approved :: MIT License
